fipper_sdk/__init__.py
fipper_sdk/exceptions.py
fipper_sdk/manager.py
fipper_sdk/utils.py
fipper_sdk/client/__init__.py
fipper_sdk/client/sync.py
fipper_sdk/clients/__init__.py
fipper_sdk/clients/async_client.py
fipper_sdk/clients/base.py
fipper_sdk/clients/sync_client.py
fipper_python_sdk-0.0.8.dist-info/LICENSE
fipper_python_sdk-0.0.8.dist-info/METADATA
fipper_python_sdk-0.0.8.dist-info/WHEEL
fipper_python_sdk-0.0.8.dist-info/top_level.txt
fipper_python_sdk-0.0.8.dist-info/RECORD
