Metadata-Version: 2.1
Name: fipper-python-sdk
Version: 0.0.8
Summary: Fipper SDK
Home-page: https://github.com/RafRaf/fipper-python-sdk
Author: RafRaf
Author-email: smartrafraf@gmail.com
License: MIT
Keywords: fipper,sdk,feature,toggle
Platform: UNKNOWN
Provides-Extra: async
Requires-Dist: aiohttp (>=3.7.3) ; extra == 'async'
Provides-Extra: sync
Requires-Dist: requests (>=2.25.1) ; extra == 'sync'
